jms_pyleftpad-0.1.1.dist-info/METADATA
jms_pyleftpad-0.1.1.dist-info/RECORD
jms_pyleftpad-0.1.1.dist-info/WHEEL
jms_pyleftpad-0.1.1.dist-info/entry_points.txt
jms_pyleftpad-0.1.1.dist-info/top_level.txt
pymyleftpad/__init__.py
pymyleftpad/cli.py
pymyleftpad/func.py
tests/__init__.py
tests/cli_test.py
tests/test_f.py
